pipegoose/__init__.py
pipegoose/constants.py
pipegoose/core/bucket/bucket.py
pipegoose/core/bucket/dist.py
pipegoose/core/bucket/exception.py
pipegoose/core/bucket/manager.py
pipegoose/core/bucket/utils.py
pipegoose/distributed/__init__.py
pipegoose/distributed/_initializers/__init__.py
pipegoose/distributed/_initializers/initialize_data.py
pipegoose/distributed/_initializers/initialize_pipeline.py
pipegoose/distributed/_initializers/initialize_tensor.py
pipegoose/distributed/_initializers/initializer.py
pipegoose/distributed/_p2p.py
pipegoose/distributed/functional.py
pipegoose/distributed/parallel_context.py
pipegoose/distributed/parallel_mode.py
pipegoose/nn/.DS_Store
pipegoose/nn/__init__.py
pipegoose/nn/data_parallel/__init__.py
pipegoose/nn/data_parallel/data_parallel.py
pipegoose/nn/expert_parallel/expert_parallel.py
pipegoose/nn/expert_parallel/experts.py
pipegoose/nn/expert_parallel/layers.py
pipegoose/nn/expert_parallel/routers.py
pipegoose/nn/moe/experts.py
pipegoose/nn/moe/layers.py
pipegoose/nn/moe/routers.py
pipegoose/nn/parallel.py
pipegoose/nn/pipeline_parallel/_comm.py
pipegoose/nn/pipeline_parallel/_job/backward.py
pipegoose/nn/pipeline_parallel/_job/callback.py
pipegoose/nn/pipeline_parallel/_job/creator.py
pipegoose/nn/pipeline_parallel/_job/forward.py
pipegoose/nn/pipeline_parallel/_job/job.py
pipegoose/nn/pipeline_parallel/_job/job_type.py
pipegoose/nn/pipeline_parallel/_job/register.py
pipegoose/nn/pipeline_parallel/_package.py
pipegoose/nn/pipeline_parallel/_utils.py
pipegoose/nn/pipeline_parallel/_worker.py
pipegoose/nn/pipeline_parallel/exception.py
pipegoose/nn/pipeline_parallel/microbatch.py
pipegoose/nn/pipeline_parallel/partitioner/tracer.py
pipegoose/nn/pipeline_parallel/partitioner.py
pipegoose/nn/pipeline_parallel/pipeline.py
pipegoose/nn/pipeline_parallel/pipeline_context.py
pipegoose/nn/pipeline_parallel/pipeline_engine.py
pipegoose/nn/pipeline_parallel/pipeline_parallel.py
pipegoose/nn/pipeline_parallel/queue.py
pipegoose-0.2.0.dist-info/LICENSE
pipegoose-0.2.0.dist-info/METADATA
pipegoose-0.2.0.dist-info/WHEEL
pipegoose-0.2.0.dist-info/RECORD
