Metadata-Version: 2.1
Name: pipegoose
Version: 0.2.0
Summary: 
License: MIT
Author: xrsrke
Author-email: hello@xrs.wtf
Requires-Python: >=3.9,<4.0
Classifier: License :: OSI Approved :: MIT License
Classifier: Programming Language :: Python :: 3
Classifier: Programming Language :: Python :: 3.9
Classifier: Programming Language :: Python :: 3.10
Classifier: Programming Language :: Python :: 3.11
Requires-Dist: datasets (>=2.13.0,<3.0.0)
Requires-Dist: einops (>=0.6.1,<0.7.0)
Requires-Dist: mkdocs (>=1.4.3,<2.0.0)
Requires-Dist: mkdocs-material (>=9.1.16,<10.0.0)
Requires-Dist: mkdocstrings (>=0.22.0,<0.23.0)
Requires-Dist: pytest-order (>=1.1.0,<2.0.0)
Requires-Dist: torch (>=2.0.1,<3.0.0)
Requires-Dist: torchtyping (>=0.1.4,<0.2.0)
Requires-Dist: transformers (>=4.30.2,<5.0.0)
